CHANGES.md
LICENSE
MANIFEST.in
README.md
setup.cfg
setup.py
wimsapi/__init__.py
wimsapi/api.py
wimsapi/exam.py
wimsapi/exceptions.py
wimsapi/item.py
wimsapi/score.py
wimsapi/sheet.py
wimsapi/user.py
wimsapi/utils.py
wimsapi/wclass.py
wimsapi.egg-info/PKG-INFO
wimsapi.egg-info/SOURCES.txt
wimsapi.egg-info/dependency_links.txt
wimsapi.egg-info/requires.txt
wimsapi.egg-info/top_level.txt